[
	{
		"__TYPE__": "SharedSliceContent",
		"variation": "default",
		"primary": {
			"heading": {
				"__TYPE__": "FieldContent",
				"value": "task",
				"type": "Text"
			},
			"content_type": {
				"__TYPE__": "FieldContent",
				"value": "Project",
				"type": "Select"
			},
			"description": {
				"__TYPE__": "StructuredTextContent",
				"value": [
					{
						"type": "paragraph",
						"content": {
							"text": "Quis nostrud laborum fugiat eu. Minim consectetur aliqua amet est. Eu excepteur irure qui deserunt occaecat cupidatat qui."
						}
					}
				]
			},
			"view_more_text": {
				"__TYPE__": "FieldContent",
				"value": "smooth",
				"type": "Text"
			},
			"fallback_item_image": {
				"__TYPE__": "ImageContent",
				"origin": {
					"id": "main",
					"url": "https://images.unsplash.com/photo-1525547719571-a2d4ac8945e2",
					"width": 3648,
					"height": 4560
				},
				"url": "https://images.unsplash.com/photo-1525547719571-a2d4ac8945e2",
				"width": 3648,
				"height": 4560,
				"edit": {
					"zoom": 1,
					"crop": {
						"x": 0,
						"y": 0
					},
					"background": "transparent"
				},
				"thumbnails": {}
			}
		},
		"items": []
	}
]